core/__init__.py
core/assistant_manager.py
core/run_manager.py
core/thread_manager.py
llm_assistant_framework-0.1.0.dist-info/METADATA
llm_assistant_framework-0.1.0.dist-info/WHEEL
llm_assistant_framework-0.1.0.dist-info/top_level.txt
llm_assistant_framework-0.1.0.dist-info/RECORD
