Metadata-Version: 2.1
Name: llm-assistant-framework
Version: 0.1.0
Summary: A flexible framework for building AI assistants using various LLMs
Home-page: https://github.com/lahfir/llm-assistant-framework
Author: Lahfir
Author-email: nmhlahfir2@gmail.com
Classifier: Development Status :: 3 - Alpha
Classifier: Intended Audience :: Developers
Classifier: License :: OSI Approved :: MIT License
Classifier: Operating System :: OS Independent
Classifier: Programming Language :: Python :: 3
Classifier: Programming Language :: Python :: 3.7
Classifier: Programming Language :: Python :: 3.8
Classifier: Programming Language :: Python :: 3.9
Classifier: Programming Language :: Python :: 3.10
Requires-Python: >=3.7
Requires-Dist: aiohttp
Requires-Dist: pydantic (>=2.0.0)
Requires-Dist: fastapi
